odoo/addons/ssi_quality_control_reference_document/README.rst
odoo/addons/ssi_quality_control_reference_document/__init__.py
odoo/addons/ssi_quality_control_reference_document/__manifest__.py
odoo/addons/ssi_quality_control_reference_document/models/__init__.py
odoo/addons/ssi_quality_control_reference_document/models/qc_worksheet.py
odoo/addons/ssi_quality_control_reference_document/static/description/icon.png
odoo14_addon_ssi_quality_control_reference_document-14.0.1.0.0.dist-info/METADATA
odoo14_addon_ssi_quality_control_reference_document-14.0.1.0.0.dist-info/WHEEL
odoo14_addon_ssi_quality_control_reference_document-14.0.1.0.0.dist-info/top_level.txt
odoo14_addon_ssi_quality_control_reference_document-14.0.1.0.0.dist-info/RECORD
